{
    "name":"vagabond",
    "title": "Vagabond",
    "description": "A system for playing Land of the Blind's TTRPG, Vagabond.",
    "author": "Dan Weiss",
    "version": "0.01",
    "minimumCoreVersion": "12.0", 
    "compatibleCoreVersion": "12.331",
    "esmodules": [
        "vagabond.js"
    ],
    "styles": [
        "vagabond.css"
    ],
    "packs": [
        {
            "name": "vagabond",
            "label": "Vagabond Compendium",
            "type": "data",
            "system": "vagabond",
            "path": "packs/vagabond.db",
            "entity": "Item"
        }
    ],
    "languages": [
        {
            "lang": "en",
            "name": "English",
            "path": "lang/en.json"
        }
    ],
    "gridDistance": 2,
    "gridUnits": "m",
    "primaryTokenAttibute": "hp",
    "initiative": {
        "formula": "1d20",
        "formulaType": "roll"
    }
}